{
"companyName": "DefaultCompany",
"productName": "WebGL_HIW",
"productVersion": "0.1",
"dataUrl": "newNewNewNewBuild.data.unityweb",
"wasmCodeUrl": "newNewNewNewBuild.wasm.code.unityweb",
"wasmFrameworkUrl": "newNewNewNewBuild.wasm.framework.unityweb",
"graphicsAPI": ["WebGL 2.0","WebGL 1.0"],
"webglContextAttributes": {"preserveDrawingBuffer": false},
"splashScreenStyle": "Dark",
"backgroundColor": "#231F20",
"cacheControl": {"default": "must-revalidate"},
"developmentBuild": false,
"multithreading": false,
"unityVersion": "2019.3.14f1"
}